over_stats/__init__.py
over_stats/errors.py
over_stats-0.4.0.dist-info/LICENSE
over_stats-0.4.0.dist-info/METADATA
over_stats-0.4.0.dist-info/WHEEL
over_stats-0.4.0.dist-info/top_level.txt
over_stats-0.4.0.dist-info/RECORD
