Metadata-Version: 2.1
Name: over-stats
Version: 0.4.0
Summary: Python API to retrieve Overwatch Statistics
Home-page: https://github.com/CRamsan/over-stats
Author: Cramsan
Author-email: contact@cramsan.com
License: GNU GPL3
Keywords: overwatch stats statistics
Platform: UNKNOWN
Classifier: Development Status :: 4 - Beta
Classifier: Environment :: Console
Classifier: Intended Audience :: Developers
Classifier: License :: OSI Approved :: GNU General Public License v3 (GPLv3)
Classifier: Operating System :: OS Independent
Classifier: Programming Language :: Python :: 3.6
Classifier: Topic :: Games/Entertainment
Classifier: Topic :: Software Development :: Libraries :: Python Modules
Requires-Python: >=3.6
Requires-Dist: requests-html
